rnsutils/__init__.py
rnsutils/instrument.py
rnsutils/lookup.py
rnsutils/sf2toxrni.py
rnsutils/sfztoxrni.py
rnsutils/utils.py
rnsutils/xrnicomment.py
rnsutils/xrniorganise.py
rnsutils/xrnireencode.py
rnsutils/xrnitag.py
rnsutils/data/empty-31.xrni
rnsutils/tests/__init__.py
rnsutils/tests/test_parse.py
rnsutils-0.9.0.dist-info/DESCRIPTION.rst
rnsutils-0.9.0.dist-info/METADATA
rnsutils-0.9.0.dist-info/RECORD
rnsutils-0.9.0.dist-info/WHEEL
rnsutils-0.9.0.dist-info/entry_points.txt
rnsutils-0.9.0.dist-info/metadata.json
rnsutils-0.9.0.dist-info/top_level.txt
